LICENSE
MANIFEST.in
README.md
requirements-dev.txt
requirements.txt
setup.cfg
setup.py
cc_plugin_ncei/__init__.py
cc_plugin_ncei/ncei_base.py
cc_plugin_ncei/ncei_grid.py
cc_plugin_ncei/ncei_point.py
cc_plugin_ncei/ncei_profile.py
cc_plugin_ncei/ncei_swath.py
cc_plugin_ncei/ncei_timeseries.py
cc_plugin_ncei/ncei_timeseries_profile.py
cc_plugin_ncei/ncei_trajectory.py
cc_plugin_ncei/ncei_trajectory_profile.py
cc_plugin_ncei/util.py
cc_plugin_ncei.egg-info/PKG-INFO
cc_plugin_ncei.egg-info/SOURCES.txt
cc_plugin_ncei.egg-info/dependency_links.txt
cc_plugin_ncei.egg-info/entry_points.txt
cc_plugin_ncei.egg-info/requires.txt
cc_plugin_ncei.egg-info/top_level.txt
cc_plugin_ncei/data/seanames.xml
cc_plugin_ncei/data/unitless.json
cc_plugin_ncei/tests/__init__.py
cc_plugin_ncei/tests/helpers.py
cc_plugin_ncei/tests/ncei_test_case.py
cc_plugin_ncei/tests/resources.py
cc_plugin_ncei/tests/test_base.py
cc_plugin_ncei/tests/test_feature_detection.py
cc_plugin_ncei/tests/test_ncei_point.py
cc_plugin_ncei/tests/test_ncei_profile.py
cc_plugin_ncei/tests/test_ncei_timeseries.py
cc_plugin_ncei/tests/test_ncei_timeseries_profile.py
cc_plugin_ncei/tests/test_ncei_trajectory.py
cc_plugin_ncei/tests/test_ncei_trajectory_profile.py
cc_plugin_ncei/tests/data/2d-regular-grid.cdl
cc_plugin_ncei/tests/data/3d-regular-grid.cdl
cc_plugin_ncei/tests/data/NCEI_point_template_v2.0_2016-09-22_181606.590413.cdl
cc_plugin_ncei/tests/data/NCEI_profile_template_v2.0_2016-09-22_181613.167269.cdl
cc_plugin_ncei/tests/data/NCEI_timeSeriesProfile_template_v2.0_2016-09-22_181615.251663.cdl
cc_plugin_ncei/tests/data/NCEI_timeSeries_template_v2.0_2016-09-22_181608.548782.cdl
cc_plugin_ncei/tests/data/NCEI_trajectoryProfile_template_v2.0_2016-09-22_181616.896731.cdl
cc_plugin_ncei/tests/data/NCEI_trajectory_template_v2.0_2016-09-22_181611.149250.cdl
cc_plugin_ncei/tests/data/NODC_point_template_v1.1_2016-06-14_125317.379316.cdl
cc_plugin_ncei/tests/data/NODC_profile_template_v1.1_2016-06-14_125318.375947.cdl
cc_plugin_ncei/tests/data/NODC_timeSeriesProfile_template_v1.1_2016-06-14_125321.546019.cdl
cc_plugin_ncei/tests/data/NODC_timeSeries_template_v1.1_2016-06-14_125320.125407.cdl
