Metadata-Version: 1.1
Name: cc-plugin-ncei
Version: 2.0.2
Summary: Compliance Checker NCEI Templates Compliance plugin
Home-page: https://github.com/ioos/cc-plugin-ncei/
Author: Luke Campbell
Author-email: luke.campbell@rpsgroup.com
License: Apache License 2.0
Platform: UNKNOWN
Classifier: Development Status :: 5 - Production/Stable
Classifier: Intended Audience :: Developers
Classifier: Intended Audience :: Science/Research
Classifier: License :: OSI Approved :: Apache Software License
Classifier: Operating System :: POSIX :: Linux
Classifier: Programming Language :: Python
Classifier: Topic :: Scientific/Engineering
